pretix_order_checkin/__init__.py
pretix_order_checkin/apps.py
pretix_order_checkin/signals.py
pretix_order_checkin/locale/django.pot
pretix_order_checkin/locale/de/LC_MESSAGES/django.mo
pretix_order_checkin/locale/de/LC_MESSAGES/django.po
pretix_order_checkin/locale/de_Informal/.gitkeep
pretix_order_checkin/locale/de_Informal/LC_MESSAGES/django.mo
pretix_order_checkin/locale/de_Informal/LC_MESSAGES/django.po
pretix_order_checkin/static/order_checkin/.gitkeep
pretix_order_checkin/templates/pretix_order_checkin/.gitkeep
pretix_order_checkin/templates/pretix_order_checkin/check_in_button.html
pretix_order_checkin/templates/pretix_order_checkin/check_out_button.html
pretix_order_checkin/templates/pretix_order_checkin/delete_check_in_button.html
pretix_order_checkin-1.1.2.dist-info/LICENSE
pretix_order_checkin-1.1.2.dist-info/METADATA
pretix_order_checkin-1.1.2.dist-info/WHEEL
pretix_order_checkin-1.1.2.dist-info/entry_points.txt
pretix_order_checkin-1.1.2.dist-info/top_level.txt
pretix_order_checkin-1.1.2.dist-info/RECORD
