Metadata-Version: 2.1
Name: pretix-order-checkin
Version: 1.1.2
Summary: Adds check-in related buttons to the order overview page.
Author-email: Daniel Malik <mail@fronbasal.de>
Maintainer-email: Daniel Malik <mail@fronbasal.de>
License: Apache
Project-URL: homepage, https://github.com/fronbasal/pretix-order-checkin
Project-URL: repository, https://github.com/fronbasal/pretix-order-checkin
Keywords: pretix
License-File: LICENSE
